MANIFEST.in
README.md
setup.py
appnvn/Hstr_StrRetrFile.py
appnvn/License_key.py
appnvn/__init__.py
appnvn/conf.py
appnvn/exazb.py
appnvn/setup.py
appnvn/RetrFile/Hsringadvance_RetrFile.py
appnvn/RetrFile/Hstr_StrRetrFile.py
appnvn/RetrFile/Lretr_file.py
appnvn/RetrFile/__init__.py
appnvn/RetrFile/hsring_RetrFile.py
appnvn/RetrFile/hstr.py
appnvn/RetrFile_RetrFolder/__init__.py
appnvn/RetrFile_RetrFolder/retr_file_folder.py
appnvn/RetrFile_RetrFolder/trans_to_parent.py
appnvn/atadctn/__init__.py
appnvn/atadctn/address.py
appnvn/atadctn/apppr.py
appnvn/atadctn/choicelayout.py
appnvn/atadctn/icontt.py
appnvn/atadctn/incustomer.py
appnvn/atadctn/indatatosel.py
appnvn/atadctn/layouttochoice.py
appnvn/atadctn/menu.py
appnvn/atadctn/opcus.py
appnvn/atadctn/reqbuild.py
appnvn/atadctn/selop.py
appnvn/atadctn/setup.py
appnvn/atadctn/spsquotation.py
appnvn/atadctn/tktable.py
appnvn/atadctn/treectn.py
appnvn/atadctn/folder/__init__.py
appnvn/atadctn/folder/inputdoc.py
appnvn/atadctn/layout/__init__.py
appnvn/atadctn/layout/mlayout.py
appnvn/balstock/__init__.py
appnvn/balstock/dataexc.py
appnvn/balstock/guibls.py
appnvn/coapp_retr/__init__.py
appnvn/coapp_retr/copyrange.py
appnvn/derowapp/__init__.py
appnvn/derowapp/delrow_advance.py
appnvn/exazp/__init__.py
appnvn/exazp/azbapp.py
appnvn/exazp/childtomotherexl.py
appnvn/exazp/conf.py
appnvn/exazp/exazb.py
appnvn/exazp/hdata.py
appnvn/exazp/excel/__init__.py
appnvn/exazp/excel/crangeactive.py
appnvn/exazp/excel/hchildsheet.py
appnvn/exazp/excel/hhm.py
appnvn/exazp/excel/itemhm.py
appnvn/exazp/sdata/__init__.py
appnvn/exazp/sdata/sdata.py
appnvn/eximexcsv/__init__.py
appnvn/eximexcsv/extocsv.py
appnvn/eximexcsv/extoex.py
appnvn/eximexcsv/templatexc/__init__.py
appnvn/rearrapp/__init__.py
appnvn/rearrapp/hfun.py
appnvn/rearrapp/mrange.py
appnvn/rearrapp/rearr_range.py
appnvn/sapp/__init__.py
pyappnvn.egg-info/PKG-INFO
pyappnvn.egg-info/SOURCES.txt
pyappnvn.egg-info/dependency_links.txt
pyappnvn.egg-info/requires.txt
pyappnvn.egg-info/top_level.txt
pynvn/__init__.py
pynvn/setup.py
pynvn/authkey/__init__.py
pynvn/autoscrollbar/__init__.py
pynvn/autoscrollbar/autoscrbar.py
