Metadata-Version: 2.1
Name: pyappnvn
Version: 0.0.4
Summary: A Python package for excel and create app.
Home-page: https://github.com/nhuannguyen1/site-packages
Author: Nhuan Nguyen
Author-email: nguyenvannhuan90123@gmail.com
License: MIT
Platform: UNKNOWN
Classifier: License :: OSI Approved :: MIT License
Classifier: Programming Language :: Python :: 3
Classifier: Programming Language :: Python :: 3.7
